edgetpu_utils/__init__.py
edgetpu_utils/benchmark.py
edgetpu_utils/partition.py
edgetpu_utils/path_utils.py
edgetpu_utils/tflite_utils.py
edgetpu_utils/partitioner/partition_with_num_ops
edgetpu_utils-1.1.4.dist-info/licenses/LICENSE
flexbuffers/__init__.py
flexbuffers/flexbuffers.py
platforms/__init__.py
platforms/darwinn/AnyHint.py
platforms/darwinn/AnyLayer.py
platforms/darwinn/DataType.py
platforms/darwinn/Description.py
platforms/darwinn/Direction.py
platforms/darwinn/DmaDescriptorHint.py
platforms/darwinn/DmaHint.py
platforms/darwinn/DmaHints.py
platforms/darwinn/Executable.py
platforms/darwinn/ExecutableType.py
platforms/darwinn/FenceHint.py
platforms/darwinn/FieldOffset.py
platforms/darwinn/InputLayer.py
platforms/darwinn/InstructionBitstream.py
platforms/darwinn/InstructionHint.py
platforms/darwinn/InterruptHint.py
platforms/darwinn/InterruptType.py
platforms/darwinn/Layer.py
platforms/darwinn/Meta.py
platforms/darwinn/MultiExecutable.py
platforms/darwinn/NumericsConstants.py
platforms/darwinn/OutputLayer.py
platforms/darwinn/OutputLayout.py
platforms/darwinn/OutputShapeInfo.py
platforms/darwinn/Package.py
platforms/darwinn/Position.py
platforms/darwinn/Range.py
platforms/darwinn/SerializedPackage.py
platforms/darwinn/TensorLayout.py
platforms/darwinn/TensorShape.py
platforms/darwinn/__init__.py
tflite/AbsOptions.py
tflite/ActivationFunctionType.py
tflite/AddNOptions.py
tflite/AddOptions.py
tflite/ArgMaxOptions.py
tflite/ArgMinOptions.py
tflite/BatchMatMulOptions.py
tflite/BatchToSpaceNDOptions.py
tflite/BidirectionalSequenceLSTMOptions.py
tflite/BidirectionalSequenceRNNOptions.py
tflite/BroadcastToOptions.py
tflite/Buffer.py
tflite/BuiltinOperator.py
tflite/BuiltinOptions.py
tflite/CallOnceOptions.py
tflite/CallOptions.py
tflite/CastOptions.py
tflite/CombinerType.py
tflite/ConcatEmbeddingsOptions.py
tflite/ConcatenationOptions.py
tflite/Conv2DOptions.py
tflite/Conv3DOptions.py
tflite/CosOptions.py
tflite/CumsumOptions.py
tflite/CustomOptionsFormat.py
tflite/CustomQuantization.py
edgetpu_utils-1.1.4.dist-info/METADATA
edgetpu_utils-1.1.4.dist-info/WHEEL
edgetpu_utils-1.1.4.dist-info/top_level.txt
edgetpu_utils-1.1.4.dist-info/RECORD
