Metadata-Version: 2.4
Name: edgetpu_utils
Version: 1.1.4
Summary: EdgeTPU utilities for model partitioning, benchmarking, and TensorFlow Lite operations
Author-email: Changhun Han <ehwjs1914@naver.com>
License: MIT License
Project-URL: Homepage, https://github.com/HanChangHun/EdgeTPU-Utils
Project-URL: Repository, https://github.com/HanChangHun/EdgeTPU-Utils
Classifier: Development Status :: 3 - Alpha
Classifier: Intended Audience :: Developers
Classifier: License :: OSI Approved :: MIT License
Classifier: Operating System :: OS Independent
Classifier: Programming Language :: Python :: 3
Classifier: Programming Language :: Python :: 3.7
Classifier: Programming Language :: Python :: 3.8
Classifier: Programming Language :: Python :: 3.9
Requires-Python: <3.10,>=3.7
License-File: LICENSE
Requires-Dist: pycoral==2.0.0
Requires-Dist: tflite_runtime==2.5.0.post1
Requires-Dist: numpy<2.0.0,>=1.16.0
Requires-Dist: pip
Requires-Dist: setuptools
Requires-Dist: flatbuffers
Requires-Dist: importlib-resources; python_version < "3.9"
Dynamic: license-file
